MANIFEST.in
README.md
setup.py
dbt/adapters/iomete/__init__.py
dbt/adapters/iomete/__version__.py
dbt/adapters/iomete/column.py
dbt/adapters/iomete/connections.py
dbt/adapters/iomete/impl.py
dbt/adapters/iomete/python_job.py
dbt/adapters/iomete/relation.py
dbt/adapters/iomete/schema_service.py
dbt/include/iomete/__init__.py
dbt/include/iomete/dbt_project.yml
dbt/include/iomete/profile_template.yml
dbt/include/iomete/macros/adapters.sql
dbt/include/iomete/macros/materializations/seed.sql
dbt/include/iomete/macros/materializations/snapshot.sql
dbt/include/iomete/macros/materializations/table.sql
dbt/include/iomete/macros/materializations/view.sql
dbt/include/iomete/macros/materializations/incremental/incremental.sql
dbt/include/iomete/macros/materializations/incremental/strategies.sql
dbt/include/iomete/macros/materializations/incremental/validate.sql
iomete_dbt_test.egg-info/PKG-INFO
iomete_dbt_test.egg-info/SOURCES.txt
iomete_dbt_test.egg-info/dependency_links.txt
iomete_dbt_test.egg-info/not-zip-safe
iomete_dbt_test.egg-info/requires.txt
iomete_dbt_test.egg-info/top_level.txt