Metadata-Version: 2.1
Name: iomete-dbt-test
Version: 1.0.1
Summary: The Apache Spark (IOMETE) adapter plugin for dbt
Home-page: https://github.com/iomete/dbt-iomete
Author: iomete
Author-email: support@iomete.com
Classifier: Development Status :: 5 - Production/Stable
Classifier: License :: OSI Approved :: Apache Software License
Classifier: Operating System :: Microsoft :: Windows
Classifier: Operating System :: MacOS :: MacOS X
Classifier: Operating System :: POSIX :: Linux
Classifier: Programming Language :: Python :: 3.7
Classifier: Programming Language :: Python :: 3.8
Classifier: Programming Language :: Python :: 3.9
Classifier: Programming Language :: Python :: 3.10
Classifier: Programming Language :: Python :: 3.11
Requires-Python: >=3.7
